varaps2/__init__.py
varaps2/main.py
varaps2/test.ipynb
varaps2/tests.ipynb
varaps2/util/VariantsProportionCoOcc.py
varaps2/util/VariantsProportionFreyja1Sparse.py
varaps2/util/VariantsProportionFreyjaSparse.py
varaps2/util/VariantsProportionLCS.py
varaps2/util/downsampling.py
varaps2/util/generate_M.py
varaps2/util/get_mutations.py
varaps2/util/helper_functions.py
varaps2/util/mode1.py
varaps2/util/mode2.py
varaps2/util/parse_position.py
varaps2/util/query_mutation_read.py
varaps2/util/read_bam_file.py
varaps2/util/refseq.py
varaps2-1.0.0.dist-info/entry_points.txt
varaps2-1.0.0.dist-info/LICENSE
varaps2-1.0.0.dist-info/WHEEL
varaps2-1.0.0.dist-info/METADATA
varaps2-1.0.0.dist-info/RECORD
